simple_poetry_package/__init__.py
simple_poetry_package/cli.py
simple_poetry_package/hello_world.py
simple_poetry_package-0.2.0.dist-info/entry_points.txt
simple_poetry_package-0.2.0.dist-info/LICENSE
simple_poetry_package-0.2.0.dist-info/METADATA
simple_poetry_package-0.2.0.dist-info/WHEEL
simple_poetry_package-0.2.0.dist-info/RECORD
