Metadata-Version: 2.1
Name: simple-poetry-package
Version: 0.2.0
Summary: 'Creating an example poetry package'
License: MIT
Author: rahul1990bhatia
Author-email: rahul1990bhatia@gmail.com
Requires-Python: >=3.11,<4.0
Classifier: License :: OSI Approved :: MIT License
Classifier: Programming Language :: Python :: 3
Classifier: Programming Language :: Python :: 3.11
Classifier: Programming Language :: Python :: 3.12
